<DOMSymbolItem xmlns:xsi="http://www.w3.org/2001/XMLSchema-instance" xmlns="http://ns.adobe.com/xfl/2008/" name="Buttongraphics/LifeSciencesButtonGraphics/CGreenHouse Assets/CDO_BeeHive Assets/BeeHiveOutline" itemID="5a1dc117-000007ea" lastModified="1511900212">
  <timeline>
    <DOMTimeline name="BeeHiveOutline">
      <layers>
        <DOMLayer name="Layer 1" color="#4F80FF" current="true" isSelected="true">
          <frames>
            <DOMFrame index="0" keyMode="9728">
              <elements>
                <DOMShape>
                  <fills>
                    <FillStyle index="1">
                      <SolidColor/>
                    </FillStyle>
                  </fills>
                  <strokes>
                    <StrokeStyle index="1">
                      <SolidStroke scaleMode="normal" weight="0.1">
                        <fill>
                          <SolidColor/>
                        </fill>
                      </SolidStroke>
                    </StrokeStyle>
                  </strokes>
                  <edges>
                    <Edge strokeStyle="1" edges="!142 -380[207 -342 259 -270!259 -270[272 -253 282 -236!282 -236[329 -160 349 -70!-137 -380[-73 -417 3 -417!3 -417[13 -417 24 -415!24 -415[88 -412 142 -380!-274 -236[-265 -256 -254 -270!-254 -270[-202 -342 -137 -380!-355 109[-348 49 -336
 -18!-336 -18[-331 -46 -325 -70!-325 -70[-312 -131 -297 -177!-297 -177[-286 -211 -274 -236"/>
                    <Edge fillStyle1="1" edges="
!-99 287[-99 264 -92 254!-92 254[-86 247 -78 244!-78 244[-76 242 -73 242!-73 242[-64 237 -53 236!-53 236|-52 234!-52 234[-48 233 -11 211!-11 211[17 200 24 203!24 203[32 206 46 220!46 220[57 231 78 250!78 250[78 251 80 251!80 251[97 270
 102 288!102 288|102 336!102 336[102 343 102 347!102 347[106 355 109 364!109 364[112 375 109 381!109 381[109 383 108 384!108 384[104 387 97 389!97 389|32 404!32 404[27 406 24 407!24 407[-13 417 -35 417!-35 417|-72 415!-72 415[-86 412
 -90 409!-90 409|-92 407!-92 407[-98 403 -98 384!-98 384|-99 287"/>
                    <Edge strokeStyle="1" edges="
!-362 231[-362 174 -355 109!-90 409[-230 407 -284 384!-284 384[-289 382 -293 380!-293 380[-295 379 -297 379!-297 379[-359 360 -365 355!-365 355[-364 335 -364 265!-364 265[-364 248 -362 231!-362 231|-78 244"/>
                    <Edge fillStyle0="1" fillStyle1="1" strokeStyle="1" edges="
!-78 244|78 250"/>
                    <Edge strokeStyle="1" edges="
!78 250|366 262!349 -70[366 2 366 86!366 86[366 97 366 109!293 392[292 401 299 404!299 404[304 406 313 406!313 406[327 398 321 395!366 262[361 329 328 384!328 384[325 390 321 395!321 395[315 392 293 392!293 392[292 392 290 392!290 392
[137 401 24 407!366 109[366 172 366 262!-355 109|366 109!-137 -380|142 -380!-274 -236|282 -236!-325 -70|349 -70"/>
                    <Edge cubics="!3 -417(;10,-417 17,-417 24,-415q3 -417Q13 -417q24 -415);"/>
                    <Edge cubics="!-254 -270(;-219,-318 -180,-355 -137,-380q-254 -270Q-202 -342q-137 -380);"/>
                    <Edge cubics="!-137 -380(;-95,-404 -48,-417 3,-417q-137 -380Q-73 -417q3 -417);"/>
                    <Edge cubics="!293 392(;292,392 292,392 290,392q293 392Q292 392q290 392);"/>
                    <Edge cubics="!299 404(;303,406 307,406 313,406q299 404Q304 406q313 406);"/>
                    <Edge cubics="!293 392(;292,398 295,403 299,404q293 392Q292 401q299 404);"/>
                    <Edge cubics="!321 395(;316,394 307,392 293,392q321 395Q315 392q293 392);"/>
                    <Edge cubics="!313 406(;323,401 326,397 321,395q313 406Q327 398q321 395);"/>
                    <Edge cubics="!-99 287(;-99,276 -99,264 -92,254q-99 287Q-99 264q-92 254);"/>
                    <Edge cubics="!109 364(;111,369 112,375 109,381q109 364Q112 375q109 381);"/>
                    <Edge cubics="!97 389(;75,394 54,400 32,404q97 389 32 404);"/>
                    <Edge cubics="!-35 417(;-47,417 -59,415 -72,415q-35 417 -72 415);"/>
                    <Edge cubics="!-92 407(;-98,403 -98,394 -98,384q-92 407Q-98 403q-98 384);"/>
                    <Edge cubics="!-98 384(;-99,352 -99,319 -99,287q-98 384 -99 287);"/>
                    <Edge cubics="!24 203(;34,206 40,214 46,220q24 203Q32 206q46 220);"/>
                    <Edge cubics="!102 288(;105,304 102,321 102,336q102 288Q102 288q102 336);"/>
                    <Edge cubics="!-52 234(;-39,223 -25,219 -11,211q-52 234Q-48 233q-11 211);"/>
                    <Edge cubics="!-11 211(;1,206 13,200 24,203q-11 211Q17 200q24 203);"/>
                    <Edge cubics="!366 86(;366,94 366,101 366,109q366 86Q366 97q366 109);"/>
                    <Edge cubics="!282 -236(;313,-185 335,-131 349,-70q282 -236Q329 -160q349 -70);"/>
                    <Edge cubics="!259 -270(;267,-259 275,-247 282,-236q259 -270Q272 -253q282 -236);"/>
                    <Edge cubics="!46 220(;54,228 64,237 78,250q46 220Q57 231q78 250);"/>
                    <Edge cubics="!78 250(;78,251 78,251 80,251q78 250Q78 251q80 251);"/>
                    <Edge cubics="!80 251(;91,264 98,276 102,288q80 251Q97 270q102 288);"/>
                    <Edge cubics="!102 336(;102,341 102,344 102,347q102 336Q102 343q102 347);"/>
                    <Edge cubics="!102 347(;105,352 108,358 109,364q102 347Q106 355q109 364);"/>
                    <Edge cubics="!349 -70(;360,-22 366,30 366,86q349 -70Q366 2q366 86);"/>
                    <Edge cubics="!78 250(;78,250 366,262 366,262q78 250 366 262);"/>
                    <Edge cubics="!366 109(;366,151 366,202 366,262q366 109Q366 172q366 262);"/>
                    <Edge cubics="!142 -380(;185,-355 224,-318 259,-270q142 -380Q207 -342q259 -270);"/>
                    <Edge cubics="!-355 109(;-350,69 -344,27 -336,-18q-355 109Q-348 49q-336 -18);"/>
                    <Edge cubics="!-336 -18(;-333,-36 -330,-53 -325,-70q-336 -18Q-331 -46q-325 -70);"/>
                    <Edge cubics="!-325 -70(;-317,-110 -307,-145 -297,-177q-325 -70 -297 -177);"/>
                    <Edge cubics="!-297 -177(;-290,-198 -282,-219 -274,-236q-297 -177 -274 -236);"/>
                    <Edge cubics="!-364 265(;-364,254 -364,242 -362,231q-364 265Q-364 248q-362 231);"/>
                    <Edge cubics="!-78 244(;-76,242 -75,242 -73,242q-78 244Q-76 242q-73 242);"/>
                    <Edge cubics="!-92 254(;-87,250 -82,245 -78,244q-92 254Q-86 247q-78 244);"/>
                    <Edge cubics="!-73 242(;-67,239 -61,237 -53,236q-73 242Q-64 237q-53 236);"/>
                    <Edge cubics="!-53 236(;-52,234 -52,234 -52,234q-53 236Q-52 234q-52 234);"/>
                    <Edge cubics="!24 407(;0,414 -21,417 -35,417q24 407Q-13 417q-35 417);"/>
                    <Edge cubics="!32 404(;29,406 26,406 24,407q32 404Q27 406q24 407);"/>
                    <Edge cubics="!-72 415(;-81,414 -87,411 -90,409q-72 415Q-86 412q-90 409);"/>
                    <Edge cubics="!-90 409(;-92,407 -92,407 -92,407q-90 409Q-92 407q-92 407);"/>
                    <Edge cubics="!-362 231(;-362,193 -359,152 -355,109q-362 231Q-362 174q-355 109);"/>
                    <Edge cubics="!-274 -236(;-268,-250 -262,-261 -254,-270q-274 -236Q-265 -256q-254 -270);"/>
                    <Edge cubics="!290 392(;188,398 100,403 24,407q290 392Q137 401q24 407);"/>
                    <Edge cubics="!-78 244(;-78,244 78,250 78,250q-78 244 78 250);"/>
                    <Edge cubics="!24 -415(;66,-414 106,-401 142,-380q24 -415Q88 -412q142 -380);"/>
                    <Edge cubics="!-325 -70(;-325,-70 349,-70 349,-70q-325 -70 349 -70);"/>
                    <Edge cubics="!-274 -236(;-274,-236 282,-236 282,-236q-274 -236 282 -236);"/>
                    <Edge cubics="!-137 -380(;-137,-380 142,-380 142,-380q-137 -380 142 -380);"/>
                    <Edge cubics="!-365 355(;-364,342 -364,312 -364,265q-365 355Q-364 335q-364 265);"/>
                    <Edge cubics="!-293 380(;-294,379 -296,379 -297,379q-293 380Q-295 379q-297 379);"/>
                    <Edge cubics="!-297 379(;-338,366 -361,358 -365,355q-297 379Q-359 360q-365 355);"/>
                    <Edge cubics="!-355 109(;-355,109 366,109 366,109q-355 109 366 109);"/>
                    <Edge cubics="!-362 231(;-362,231 -78,244 -78,244q-362 231 -78 244);"/>
                    <Edge cubics="!-284 384(;-287,383 -290,381 -293,380q-284 384Q-289 382q-293 380);"/>
                    <Edge cubics="!109 381(;109,382 109,383 108,384q109 381Q109 383q108 384);"/>
                    <Edge cubics="!108 384(;105,386 102,388 97,389q108 384Q104 387q97 389);"/>
                    <Edge cubics="!366 262(;363,307 350,347 328,384q366 262Q361 329q328 384);"/>
                    <Edge cubics="!328 384(;326,388 324,392 321,395q328 384Q325 390q321 395);"/>
                    <Edge cubics="!-90 409(;-183,408 -248,399 -284,384q-90 409Q-230 407q-284 384);"/>
                  </edges>
                </DOMShape>
              </elements>
            </DOMFrame>
          </frames>
        </DOMLayer>
      </layers>
    </DOMTimeline>
  </timeline>
</DOMSymbolItem>