<DOMSymbolItem xmlns:xsi="http://www.w3.org/2001/XMLSchema-instance" xmlns="http://ns.adobe.com/xfl/2008/" name="Buttongraphics/Forces&amp;#038MotionButtonGraphics/Ramp/RampSim Assets/CBase Assets/CbaseNull" itemID="48bac724-000001e9" linkageExportForAS="true" linkageClassName="CbaseNull" sourceFlashFilepath="../EFMod_RQIntro/EFMod_RQModIntro.xfl" sourceLibraryItemHRef="Buttongraphics/Forces&amp;MotionButtonGraphics/Ramp/RampSim Assets/CBase Assets/CbaseNull" sourceLastModified="1514998902" lastModified="1514998902" sourceItemID="00000000-ffffffff">
  <timeline>
    <DOMTimeline name="CbaseNull">
      <layers>
        <DOMLayer name="Layer 1" color="#4FFF4F" current="true" isSelected="true">
          <frames>
            <DOMFrame index="0" keyMode="9728">
              <elements>
                <DOMShape>
                  <fills>
                    <FillStyle index="1">
                      <SolidColor color="#999999"/>
                    </FillStyle>
                  </fills>
                  <strokes>
                    <StrokeStyle index="1">
                      <SolidStroke scaleMode="normal" weight="2">
                        <fill>
                          <SolidColor/>
                        </fill>
                      </SolidStroke>
                    </StrokeStyle>
                    <StrokeStyle index="2">
                      <SolidStroke scaleMode="normal" weight="1.35">
                        <fill>
                          <SolidColor/>
                        </fill>
                      </SolidStroke>
                    </StrokeStyle>
                  </strokes>
                  <edges>
                    <Edge strokeStyle="2" edges="!477 35[480 88 436.5 190"/>
                    <Edge fillStyle0="1" edges="!436.5 190|477 35!477 35[#1E1.76 #10.EA 485 0"/>
                    <Edge fillStyle0="1" strokeStyle="1" edges="!485 0/-5415 0!-5415 0/-5415 190!-5415 190/436.5 190"/>
                    <Edge cubics="!7070 190(;7070,190 7070,40 7070,40q7070 190 7070 40);"/>
                    <Edge cubics="!7070 40(;7070,40 7070,-157 7070,-157q7070 40 7070 -157);"/>
                    <Edge cubics="!7070 -157(;7070,-157 6740,-157 6740,-157q7070 -157 6740 -157);"/>
                    <Edge cubics="!6740 -157(;6740,-157 6740,0 6740,0q6740 -157 6740 0);"/>
                    <Edge cubics="!6740 0(;6740,0 1031,0 1031,0q6740 0 1031 0);"/>
                    <Edge cubics="!1031 0(;1031,0 778,0 778,0q1031 0 778 0);"/>
                    <Edge cubics="!778 0(;778,0 706,0 706,0q778 0 706 0);"/>
                    <Edge cubics="!706 0(;706,0 -5415,0 -5415,0q706 0 -5415 0);"/>
                    <Edge cubics="!-5415 0(;-5415,0 -5415,190 -5415,190q-5415 0 -5415 190);"/>
                    <Edge cubics="!-5415 190(;-5415,190 753,190 753,190q-5415 190 753 190);"/>
                    <Edge cubics="!753 190(;753,190 795,190 795,190q753 190 795 190);"/>
                    <Edge cubics="!795 190(;795,190 1062,190 1062,190q795 190 1062 190);"/>
                    <Edge cubics="!1062 190(;1062,190 1136,190 1136,190q1062 190 1136 190);"/>
                    <Edge cubics="!1136 190(;1136,190 4267,190 4267,190q1136 190 4267 190);"/>
                    <Edge cubics="!4267 190(;4267,190 7070,190 7070,190q4267 190 7070 190);"/>
                    <Edge cubics="!809 -84(;835,-113 874,-133 913,-130q809 -84Q829 -107q856 -119Q885 -132q913 -130);"/>
                    <Edge cubics="!913 -130(;952,-126 991,-100 1010,-68q913 -130Q942 -127q969 -109Q996 -92q1010 -68);"/>
                    <Edge cubics="!1010 -68(;1023,-42 1030,-9 1033,16q1010 -68Q1027 -34q1033 16);"/>
                    <Edge cubics="!1033 16(;1044,75 1054,135 1062,190q1033 16 1062 190);"/>
                    <Edge cubics="!1062 190(;1071,244 1078,293 1085,341q1062 190 1085 341);"/>
                    <Edge cubics="!1085 341(;1092,390 1098,435 1092,484q1085 341Q1098 433q1092 484);"/>
                    <Edge cubics="!1092 484(;1085,533 1059,578 1017,601q1092 484Q1080 566q1017 601);"/>
                    <Edge cubics="!1017 601(;975,620 919,614 884,581q1017 601Q985 616q948 611Q910 605q884 581);"/>
                    <Edge cubics="!884 581(;848,546 838,490 832,442q884 581Q845 543q832 442);"/>
                    <Edge cubics="!832 442(;819,359 807,276 795,190q832 442 795 190);"/>
                    <Edge cubics="!795 190(;791,165 787,138 783,110q795 190 783 110);"/>
                    <Edge cubics="!783 110(;773,42 767,-32 809,-84q783 110Q774 46q777 7Q781 -49q809 -84);"/>
                    <Edge cubics="!6477 364(;6444,390 6405,393 6363,390q6477 364Q6437 395q6363 390);"/>
                    <Edge cubics="!6363 390(;6298,393 6233,393 6168,393q6363 390Q6298 393q6168 393);"/>
                    <Edge cubics="!6168 393(;4667,419 3162,373 1664,260q6168 393Q3939 432q1664 260);"/>
                    <Edge cubics="!1664 260(;1608,256 1550,240 1521,191q1664 260Q1557 252q1521 191);"/>
                    <Edge cubics="!1521 191(;1495,130 1540,58 1602,32q1521 191Q1502 147q1529 98Q1554 52q1602 32);"/>
                    <Edge cubics="!1602 32(;1660,3 1729,9 1797,9q1602 32Q1640 13q1696 10Q1705 9q1797 9);"/>
                    <Edge cubics="!1797 9(;3269,48 4741,91 6214,133q1797 9Q2759 35q6214 133);"/>
                    <Edge cubics="!6214 133(;6292,133 6373,130 6438,169q6214 133Q6300 133q6331 136Q6395 143q6438 169);"/>
                    <Edge cubics="!6438 169(;6503,208 6535,312 6477,360q6438 169Q6489 200q6504 261Q6519 325q6477 360);"/>
                    <Edge cubics="!6955 52(;6874,54 6793,55 6706,56q6955 52 6706 56);"/>
                    <Edge cubics="!6706 56(;6471,58 6230,62 5989,84q6706 56 6472 59 5989 84);"/>
                    <Edge cubics="!5989 84(;5781,104 5577,139 5372,156q5989 84Q5895 93q5679 121Q5481 147q5372 156);"/>
                    <Edge cubics="!5372 156(;5226,165 5083,169 4936,172q5372 156Q5200 167q4936 172);"/>
                    <Edge cubics="!4936 172(;4787,178 4634,182 4485,185q4936 172Q4741 180q4485 185);"/>
                    <Edge cubics="!4485 185(;4414,187 4343,189 4267,190q4485 185 4267 190);"/>
                    <Edge cubics="!4267 190(;3232,214 2192,234 1153,191q4267 190Q3317 211q2818 215Q1892 222q1153 191);"/>
                    <Edge cubics="!1153 191(;1127,190 1099,187 1061,180q1153 191 1061 180);"/>
                    <Edge cubics="!1061 180(;979,164 892,123 887,39q1061 180 980 154Q891 114q887 39);"/>
                    <Edge cubics="!887 39(;884,-32 952,-94 1023,-110q887 39Q885 -12q927 -56Q967 -97q1023 -110);"/>
                    <Edge cubics="!1023 -110(;1098,-126 1173,-107 1244,-94q1023 -110Q1072 -120q1135 -113Q1152 -111q1244 -94);"/>
                    <Edge cubics="!1244 -94(;1517,-45 1794,-48 2067,-55q1244 -94Q1428 -61q1656 -53Q1811 -48q2067 -55);"/>
                    <Edge cubics="!2067 -55(;2687,-65 3305,-78 3922,-87q2067 -55Q2687 -65q3922 -87);"/>
                    <Edge cubics="!3922 -87(;4325,-94 4725,-104 5128,-126q3922 -87Q4643 -99q5128 -126);"/>
                    <Edge cubics="!5128 -126(;5768,-162 6409,-237 7049,-188q5128 -126Q5448 -144q6089 -189Q6647 -219q7049 -188);"/>
                    <Edge cubics="!7049 -188(;7094,-182 7146,-175 7176,-136q7049 -188Q7096 -182q7118 -174Q7156 -162q7176 -136);"/>
                    <Edge cubics="!7176 -136(;7211,-87 7182,-13 7130,16q7176 -136Q7202 -100q7186 -52Q7170 -6q7130 16);"/>
                    <Edge cubics="!7130 16(;7113,27 7095,34 7070,40q7130 16 7070 40);"/>
                    <Edge cubics="!7070 40(;7038,50 6996,52 6955,52q7070 40Q7022 52q6955 52);"/>
                    <Edge cubics="!2128 -22(;2291,-123 2496,-136 2687,-149q2128 -22Q2236 -89q2397 -118Q2490 -136q2687 -149);"/>
                    <Edge cubics="!2687 -149(;2876,-159 3064,-169 3250,-178q2687 -149Q3076 -170q3250 -178);"/>
                    <Edge cubics="!3250 -178(;3610,-195 3968,-214 4329,-201q3250 -178Q3639 -196q3789 -201Q4091 -210q4329 -201);"/>
                    <Edge cubics="!4329 -201(;5126,-169 5915,25 6706,56q4329 -201Q4641 -188q5059 -135Q5302 -105q5787 -34Q6304 37q6706 56);"/>
                    <Edge cubics="!6706 56(;6828,63 6949,64 7070,60q6706 56Q6902 64q7070 60);"/>
                    <Edge cubics="!7070 60(;7130,59 7187,56 7244,52q7070 60 7244 52);"/>
                    <Edge cubics="!7244 52(;7306,45 7371,42 7429,65q7244 52Q7363 39q7429 65);"/>
                    <Edge cubics="!7429 65(;7484,87 7533,149 7517,208q7429 65Q7473 83q7500 123Q7528 166q7517 208);"/>
                    <Edge cubics="!7517 208(;7497,282 7406,305 7328,312q7517 208Q7493 297q7328 312);"/>
                    <Edge cubics="!7328 312(;7163,318 6994,295 6825,312q7328 312Q7265 314q7078 308Q6920 302q6825 312);"/>
                    <Edge cubics="!6825 312(;6636,328 6454,390 6266,416q6825 312Q6721 321q6545 360Q6345 405q6266 416);"/>
                    <Edge cubics="!6266 416(;6142,432 6012,432 5885,429q6266 416Q6122 435q5885 429);"/>
                    <Edge cubics="!5885 429(;5125,425 4364,422 3604,416q5885 429Q3982 419q3604 416);"/>
                    <Edge cubics="!3604 416(;3542,416 3471,409 3441,354q3604 416Q3546 416q3511 406Q3461 391q3441 354);"/>
                    <Edge cubics="!3441 354(;3412,302 3445,237 3497,204q3441 354Q3420 317q3439 272Q3456 230q3497 204);"/>
                    <Edge cubics="!3497 204(;3545,175 3607,172 3666,169q3497 204Q3529 185q3577 177Q3606 172q3666 169);"/>
                    <Edge cubics="!3666 169(;4088,156 4511,143 4936,126q3666 169Q4514 143q4936 126);"/>
                    <Edge cubics="!4936 126(;4176,133 3419,136 2661,143q4936 126Q3419 136q2661 143);"/>
                    <Edge cubics="!2661 143(;2479,143 2275,152 2151,286q2661 143Q2484 143q2384 164Q2234 196q2151 286);"/>
                    <Edge cubics="!2151 286(;2379,295 2606,305 2834,315q2151 286 2834 315);"/>
                    <Edge cubics="!2834 315(;2908,318 3006,338 3019,412q2834 315Q2903 318q2949 337Q3010 362q3019 412);"/>
                    <Edge cubics="!3019 412(;3029,461 2993,510 2947,533q3019 412Q3026 447q3004 482Q2983 515q2947 533);"/>
                    <Edge cubics="!2947 533(;2905,552 2853,555 2804,555q2947 533Q2898 555q2804 555);"/>
                    <Edge cubics="!2804 555(;2275,565 1742,572 1222,474q2804 555Q2288 565q2010 555Q1570 540q1222 474);"/>
                    <Edge cubics="!1222 474(;1111,451 975,399 971,286q1222 474Q1119 453q1056 414Q974 363q971 286);"/>
                    <Edge cubics="!971 286(;971,208 1040,146 1069,71q971 286Q971 241q1009 177Q1061 91q1069 71);"/>
                    <Edge cubics="!1069 71(;1114,-35 1088,-195 1192,-253q1069 71Q1075 56q1108 -109Q1130 -219q1192 -253);"/>
                    <Edge cubics="!1192 -253(;1296,-308 1413,-211 1469,-107q1192 -253Q1265 -291q1349 -240Q1422 -194q1469 -107);"/>
                    <Edge cubics="!1469 -107(;1524,-6 1566,117 1677,159q1469 -107Q1497 -56q1552 48Q1606 132q1677 159);"/>
                    <Edge cubics="!1677 159(;1833,221 1982,61 2128,-22q1677 159Q1775 198q1906 123Q1981 80q2128 -22);"/>
                    <Edge cubics="!8010 130(;8047,130 8093,140 8099,174q8010 130Q8043 130q8066 139Q8095 151q8099 174);"/>
                    <Edge cubics="!8099 174(;8108,221 8045,242 7997,242q8099 174Q8105 206q8069 226Q8039 242q7997 242);"/>
                    <Edge cubics="!7997 242(;7872,245 7745,249 7618,250q7997 242Q7686 249q7618 250);"/>
                    <Edge cubics="!7618 250(;7316,259 7015,265 6713,272q7618 250Q7464 255q6713 272);"/>
                    <Edge cubics="!6713 272(;6674,272 6628,272 6600,244q6713 272Q6672 272q6652 269Q6619 263q6600 244);"/>
                    <Edge cubics="!6600 244(;6570,216 6583,151 6624,153q6600 244Q6577 223q6585 187Q6594 152q6624 153);"/>
                    <Edge cubics="!6624 153(;6570,132 6571,49 6613,11q6624 153Q6585 138q6583 88Q6580 41q6613 11);"/>
                    <Edge cubics="!6613 11(;6656,-26 6717,-31 6773,-33q6613 11Q6642 -14q6688 -24Q6720 -31q6773 -33);"/>
                    <Edge cubics="!6773 -33(;6931,-39 7090,-39 7248,-29q6773 -33Q7030 -43q7248 -29);"/>
                    <Edge cubics="!7248 -29(;7283,-28 7322,-21 7334,8q7248 -29Q7320 -27q7334 8);"/>
                    <Edge cubics="!7334 8(;7349,46 7304,82 7264,89q7334 8Q7345 35q7320 60Q7297 83q7264 89);"/>
                    <Edge cubics="!7264 89(;7225,94 7182,85 7144,99q7264 89Q7254 90q7204 91Q7166 91q7144 99);"/>
                    <Edge cubics="!7144 99(;7433,108 7722,120 8010,130q7144 99Q7433 108q8010 130);"/>
                    <Edge cubics="!891 160(;889,199 879,240 864,278q891 160Q888 217q864 278);"/>
                    <Edge cubics="!864 278(;854,301 841,323 841,348q864 278Q859 290q849 312Q841 332q841 348);"/>
                    <Edge cubics="!841 348(;839,366 844,386 838,404q841 348Q840 353q841 376Q841 394q838 404);"/>
                    <Edge cubics="!838 404(;829,425 803,437 778,438q838 404Q832 419q814 429Q798 437q778 438);"/>
                    <Edge cubics="!778 438(;754,440 730,435 706,435q778 438Q765 439q742 437Q715 435q706 435);"/>
                    <Edge cubics="!706 435(;688,435 668,438 651,430q706 435Q688 436q678 436Q662 435q651 430);"/>
                    <Edge cubics="!651 430(;617,412 620,361 643,330q651 430Q627 417q626 385Q625 355q643 330);"/>
                    <Edge cubics="!643 330(;666,300 701,280 724,250q643 330Q655 315q684 290Q713 265q724 250);"/>
                    <Edge cubics="!724 250(;738,233 747,213 753,190q724 250Q746 223q753 190);"/>
                    <Edge cubics="!753 190(;758,164 758,135 752,107q753 190Q762 153q752 107);"/>
                    <Edge cubics="!752 107(;740,57 716,13 688,-26q752 107Q736 41q688 -26);"/>
                    <Edge cubics="!688 -26(;668,-57 645,-95 661,-128q688 -26Q668 -57q661 -76Q650 -106q661 -128);"/>
                    <Edge cubics="!661 -128(;674,-155 711,-165 739,-156q661 -128Q670 -148q694 -155Q717 -163q739 -156);"/>
                    <Edge cubics="!739 -156(;768,-146 790,-125 808,-100q739 -156Q777 -143q808 -100);"/>
                    <Edge cubics="!808 -100(;866,-28 895,66 891,160q808 -100Q851 -46q873 22Q894 89q891 160);"/>
                    <Edge cubics="!744 457(;721,438 719,405 719,376q744 457Q719 436q719 376);"/>
                    <Edge cubics="!719 376(;719,247 719,118 719,-8q719 376 719 -8);"/>
                    <Edge cubics="!719 -8(;721,-36 722,-69 744,-85q719 -8Q721 -39q724 -51Q730 -74q744 -85);"/>
                    <Edge cubics="!744 -85(;772,-108 816,-92 834,-61q744 -85Q764 -102q793 -93Q820 -85q834 -61);"/>
                    <Edge cubics="!834 -61(;853,-31 854,4 854,39q834 -61Q854 -29q854 39);"/>
                    <Edge cubics="!854 39(;853,136 853,232 853,330q854 39 853 330);"/>
                    <Edge cubics="!853 330(;853,364 851,402 833,430q853 330Q853 399q833 430);"/>
                    <Edge cubics="!833 430(;815,460 772,478 744,457q833 430Q819 454q792 463Q764 472q744 457);"/>
                    <Edge cubics="!740 -196(;768,-199 795,-178 806,-151q740 -196Q760 -198q779 -185Q798 -172q806 -151);"/>
                    <Edge cubics="!806 -151(;818,-125 818,-97 820,-67q806 -151Q814 -134q817 -110Q818 -104q820 -67);"/>
                    <Edge cubics="!820 -67(;823,-11 831,42 841,97q820 -67Q824 2q841 97);"/>
                    <Edge cubics="!841 97(;853,156 867,214 876,272q841 97Q874 260q876 272);"/>
                    <Edge cubics="!876 272(;887,346 886,420 886,495q876 272Q886 339q886 495);"/>
                    <Edge cubics="!886 495(;886,564 886,633 884,704q886 495Q886 633q884 704);"/>
                    <Edge cubics="!884 704(;884,752 872,813 825,821q884 704Q884 748q872 778Q857 816q825 821);"/>
                    <Edge cubics="!825 821(;796,825 768,803 757,775q825 821Q804 824q784 810Q766 797q757 775);"/>
                    <Edge cubics="!757 775(;745,749 745,717 747,689q757 775Q743 745q747 689);"/>
                    <Edge cubics="!747 689(;752,575 760,462 749,349q747 689Q754 540q754 519Q756 422q749 349);"/>
                    <Edge cubics="!749 349(;742,290 730,232 721,173q749 349Q730 232q721 173);"/>
                    <Edge cubics="!721 173(;706,94 694,13 684,-64q721 173Q701 69q684 -64);"/>
                    <Edge cubics="!684 -64(;681,-90 678,-118 686,-145q684 -64Q678 -117q686 -145);"/>
                    <Edge cubics="!686 -145(;693,-169 714,-194 740,-196q686 -145Q692 -164q706 -179Q722 -195q740 -196);"/>
                    <Edge cubics="!726 163(;733,200 738,235 744,270q726 163 744 270);"/>
                    <Edge cubics="!744 270(;750,302 755,334 757,366q744 270Q755 326q757 366);"/>
                    <Edge cubics="!757 366(;764,425 764,483 756,542q757 366Q768 456q756 542);"/>
                    <Edge cubics="!756 542(;754,566 747,595 724,604q756 542Q752 593q724 604);"/>
                    <Edge cubics="!724 604(;700,614 672,596 661,573q724 604Q707 611q688 601Q670 591q661 573);"/>
                    <Edge cubics="!661 573(;651,549 653,522 653,496q661 573Q655 558q653 535Q653 531q653 496);"/>
                    <Edge cubics="!653 496(;657,396 643,296 622,198q653 496Q658 367q622 198);"/>
                    <Edge cubics="!622 198(;616,166 608,133 600,102q622 198Q615 159q600 102);"/>
                    <Edge cubics="!600 102(;592,70 583,37 578,0q600 102 578 0);"/>
                    <Edge cubics="!578 0(;575,-13 573,-30 573,-46q578 0 573 -46);"/>
                    <Edge cubics="!573 -46(;573,-67 574,-88 585,-106q573 -46Q573 -86q585 -106);"/>
                    <Edge cubics="!585 -106(;596,-123 617,-136 638,-130q585 -106Q594 -120q608 -127Q623 -134q638 -130);"/>
                    <Edge cubics="!638 -130(;660,-123 670,-96 677,-72q638 -130Q662 -122q677 -72);"/>
                    <Edge cubics="!677 -72(;690,-23 702,24 711,75q677 -72Q701 19q711 75);"/>
                    <Edge cubics="!711 75(;717,104 722,133 726,163q711 75Q720 119q726 163);"/>
                    <Edge cubics="!611 6(;617,-15 627,-37 630,-61q611 6Q614 -4q622 -26Q628 -46q630 -61);"/>
                    <Edge cubics="!630 -61(;633,-78 633,-96 642,-110q630 -61Q632 -69q634 -87Q636 -101q642 -110);"/>
                    <Edge cubics="!642 -110(;657,-133 695,-131 715,-111q642 -110Q653 -127q677 -127Q700 -126q715 -111);"/>
                    <Edge cubics="!715 -111(;734,-92 739,-61 735,-33q715 -111Q742 -84q735 -33);"/>
                    <Edge cubics="!735 -33(;731,-6 720,18 715,45q735 -33Q733 -19q725 6Q717 33q715 45);"/>
                    <Edge cubics="!715 45(;707,80 705,117 705,152q715 45Q705 89q705 152);"/>
                    <Edge cubics="!705 152(;705,180 705,208 711,235q705 152Q705 208q711 235);"/>
                    <Edge cubics="!711 235(;717,267 733,300 731,334q711 235Q712 238q724 284Q732 314q731 334);"/>
                    <Edge cubics="!731 334(;730,367 703,405 669,397q731 334Q730 361q712 381Q693 403q669 397);"/>
                    <Edge cubics="!669 397(;647,392 633,370 625,348q669 397Q640 391q625 348);"/>
                    <Edge cubics="!625 348(;614,321 611,292 607,263q625 348Q616 325q607 263);"/>
                    <Edge cubics="!607 263(;604,240 602,217 602,190q607 263 602 190);"/>
                    <Edge cubics="!602 190(;600,170 600,147 600,124q602 190 600 124);"/>
                    <Edge cubics="!600 124(;600,85 600,44 611,6q600 124Q600 44q611 6);"/>
                    <Edge cubics="!603 318(;583,336 559,352 533,352q603 318Q565 352q533 352);"/>
                    <Edge cubics="!533 352(;505,353 477,334 474,306q533 352Q511 353q494 340Q476 327q474 306);"/>
                    <Edge cubics="!474 306(;470,273 507,249 530,223q474 306Q472 285q492 262Q504 249q530 223);"/>
                    <Edge cubics="!530 223(;561,189 574,143 577,96q530 223Q572 177q577 96);"/>
                    <Edge cubics="!577 96(;579,50 574,5 574,-39q577 96Q579 50q574 -39);"/>
                    <Edge cubics="!574 -39(;574,-58 574,-79 582,-97q574 -39Q574 -79q582 -97);"/>
                    <Edge cubics="!582 -97(;590,-114 608,-130 627,-130q582 -97Q588 -111q600 -120Q613 -130q627 -130);"/>
                    <Edge cubics="!627 -130(;650,-130 669,-110 676,-89q627 -130Q643 -130q658 -117Q670 -106q676 -89);"/>
                    <Edge cubics="!676 -89(;683,-67 681,-44 681,-22q676 -89Q681 -73q681 -22);"/>
                    <Edge cubics="!681 -22(;679,58 694,143 668,219q681 -22Q680 18q684 100Q684 172q668 219);"/>
                    <Edge cubics="!668 219(;655,257 633,291 603,318q668 219Q648 278q603 318);"/>
                    <Edge cubics="!605 438(;586,453 555,453 538,435q605 438Q590 450q571 449Q551 448q538 435);"/>
                    <Edge cubics="!538 435(;518,417 517,387 523,362q538 435Q511 411q523 362);"/>
                    <Edge cubics="!523 362(;530,336 543,313 548,287q523 362Q543 313q548 287);"/>
                    <Edge cubics="!548 287(;555,250 546,211 553,175q548 287Q552 269q551 231Q550 193q553 175);"/>
                    <Edge cubics="!553 175(;562,127 601,87 607,39q553 175Q557 152q581 107Q604 64q607 39);"/>
                    <Edge cubics="!607 39(;611,3 598,-29 599,-63q607 39Q609 19q604 -13Q599 -48q599 -63);"/>
                    <Edge cubics="!599 -63(;601,-98 629,-137 663,-130q599 -63Q601 -91q619 -112Q639 -135q663 -130);"/>
                    <Edge cubics="!663 -130(;695,-123 704,-80 707,-46q663 -130Q700 -122q707 -46);"/>
                    <Edge cubics="!707 -46(;711,15 716,80 694,141q707 -46Q711 18q710 48Q709 101q694 141);"/>
                    <Edge cubics="!694 141(;682,170 666,196 659,226q694 141Q688 156q675 183Q663 208q659 226);"/>
                    <Edge cubics="!659 226(;652,253 653,280 651,308q659 226Q655 243q653 267Q652 280q651 308);"/>
                    <Edge cubics="!651 308(;647,336 638,364 629,391q651 308Q647 338q629 391);"/>
                    <Edge cubics="!629 391(;624,408 618,426 605,438q629 391Q619 425q605 438);"/>
                    <Edge cubics="!594 278(;582,312 561,340 555,375q594 278Q590 289q572 326Q558 355q555 375);"/>
                    <Edge cubics="!555 375(;549,400 552,425 547,449q555 375Q552 388q551 412Q549 438q547 449);"/>
                    <Edge cubics="!547 449(;542,474 525,499 500,503q547 449Q543 469q531 484Q518 500q500 503);"/>
                    <Edge cubics="!500 503(;464,507 440,464 439,427q500 503Q475 506q456 480Q440 457q439 427);"/>
                    <Edge cubics="!439 427(;435,369 460,313 478,257q439 427Q436 390q450 341Q469 285q478 257);"/>
                    <Edge cubics="!478 257(;497,196 510,132 517,68q478 257Q506 166q517 68);"/>
                    <Edge cubics="!517 68(;523,2 523,-67 565,-119q517 68Q525 -15q528 -31Q538 -85q565 -119);"/>
                    <Edge cubics="!565 -119(;578,-136 596,-150 617,-153q565 -119Q588 -149q617 -153);"/>
                    <Edge cubics="!617 -153(;639,-157 663,-146 670,-127q617 -153Q634 -156q649 -149Q665 -141q670 -127);"/>
                    <Edge cubics="!670 -127(;679,-102 664,-78 652,-54q670 -127Q676 -111q669 -90Q666 -83q652 -54);"/>
                    <Edge cubics="!652 -54(;633,-11 627,33 622,80q652 -54Q631 -7q622 80);"/>
                    <Edge cubics="!622 80(;618,115 614,150 612,185q622 80Q614 150q612 185);"/>
                    <Edge cubics="!612 185(;608,217 605,249 594,278q612 185Q604 253q594 278);"/>
                    <Edge cubics="!496 -92(;497,-123 497,-162 526,-175q496 -92Q497 -126q501 -140Q507 -166q526 -175);"/>
                    <Edge cubics="!526 -175(;547,-187 574,-175 587,-157q526 -175Q541 -184q560 -177Q577 -171q587 -157);"/>
                    <Edge cubics="!587 -157(;601,-137 605,-113 605,-89q587 -157Q605 -131q605 -89);"/>
                    <Edge cubics="!605 -89(;608,-3 581,79 557,161q605 -89Q607 -33q591 38Q584 68q557 161);"/>
                    <Edge cubics="!557 161(;534,244 514,327 499,412q557 161Q519 297q499 412);"/>
                    <Edge cubics="!499 412(;495,438 490,465 473,486q499 412Q491 464q473 486);"/>
                    <Edge cubics="!473 486(;445,516 386,510 373,473q473 486Q452 509q417 505Q383 501q373 473);"/>
                    <Edge cubics="!373 473(;367,456 373,436 377,419q373 473Q368 458q377 419);"/>
                    <Edge cubics="!377 419(;397,341 418,262 439,184q377 419 439 184);"/>
                    <Edge cubics="!439 184(;452,135 465,84 477,35q439 184 477 35);"/>
                    <Edge cubics="!477 35(;487,-6 495,-49 496,-92q477 35Q495 -38q496 -92);"/>
                  </edges>
                </DOMShape>
              </elements>
            </DOMFrame>
          </frames>
        </DOMLayer>
      </layers>
    </DOMTimeline>
  </timeline>
</DOMSymbolItem>